leafnlp/__init__.py
leafnlp/version.py
leafnlp/ml/__init__.py
leafnlp/ml/modules/activation/__init__.py
leafnlp/ml/modules/activation/functions.py
leafnlp/ml/modules/attention/__init__.py
leafnlp/ml/modules/attention/attention_concepts.py
leafnlp/ml/modules/attention/attention_cross.py
leafnlp/ml/modules/attention/attention_multi_head.py
leafnlp/ml/modules/attention/attention_self.py
leafnlp/ml/modules/decoder/__init__.py
leafnlp/ml/modules/decoder/decoder_transformer.py
leafnlp/ml/modules/decoding/__init__.py
leafnlp/ml/modules/decoding/word_copy.py
leafnlp/ml/modules/embedding/__init__.py
leafnlp/ml/modules/embedding/bert_embedding.py
leafnlp/ml/modules/embedding/position_embedding.py
leafnlp/ml/modules/encoder/__init__.py
leafnlp/ml/modules/encoder/encoder_cnn.py
leafnlp/ml/modules/encoder/encoder_rnn.py
leafnlp/ml/modules/encoder/encoder_transformer.py
leafnlp/ml/modules/utils/CompressionFM.py
leafnlp/ml/modules/utils/Highway.py
leafnlp/ml/modules/utils/LayerNormalization.py
leafnlp/ml/modules/utils/PositionwiseFeedForward.py
leafnlp/ml/modules/utils/__init__.py
leafnlp/ml/sequence_tagging/__init__.py
leafnlp/ml/sequence_tagging/bert.py
leafnlp/nlp/__init__.py
leafnlp/nlp/event_detection/__init__.py
leafnlp/nlp/event_detection/bert.py
leafnlp/nlp/event_detection/utils.py
leafnlp/nlp/named_entity_recogonition/__init__.py
leafnlp/nlp/named_entity_recogonition/bert.py
leafnlp/nlp/named_entity_recogonition/utils.py
leafnlp/nlp/text_ranking/__init__.py
leafnlp/nlp/text_ranking/bm25.py
leafnlp/nlp/text_similarity/lexicon_matching.py
leafnlp/nlp/tokenizer/__init__.py
leafnlp/nlp/tokenizer/sent_tokenizer.py
leafnlp/nlp/tokenizer/text_cleaner.py
leafnlp/nlp/tokenizer/word_tokenizer.py
leafnlp/nlp/tokenizer/word_tokenizer_bert.py
leafnlp-0.0.17.dist-info/LICENSE
leafnlp-0.0.17.dist-info/METADATA
leafnlp-0.0.17.dist-info/WHEEL
leafnlp-0.0.17.dist-info/top_level.txt
leafnlp-0.0.17.dist-info/RECORD
