Metadata-Version: 2.1
Name: leafnlp
Version: 0.0.17
Summary: Domain-specific Natural Language Processing with LeafNLP
Home-page: https://leafnlp.org
Author: The LeafNLP Team
Author-email: 
License: UNKNOWN
Keywords: leafnlp NLP Deep Learning
Platform: UNKNOWN
Classifier: Intended Audience :: Science/Research
Classifier: Development Status :: 3 - Alpha
Classifier: License :: OSI Approved :: Apache Software License
Classifier: Programming Language :: Python :: 3
Classifier: Topic :: Scientific/Engineering :: Artificial Intelligence
Requires-Python: >=3.8.10
Requires-Dist: numpy (==1.21.2)
Requires-Dist: scikit-learn (==1.0)
Requires-Dist: torch (==1.9.1)
Requires-Dist: torchvision (==0.10.1)
Requires-Dist: tqdm (==4.49.0)
Requires-Dist: transformers (==4.11.2)
